style_doc/__init__.py
style_doc/__main__.py
style_doc/style_doc.py
style_doc-0.2.0.dist-info/LICENSE
style_doc-0.2.0.dist-info/METADATA
style_doc-0.2.0.dist-info/WHEEL
style_doc-0.2.0.dist-info/entry_points.txt
style_doc-0.2.0.dist-info/top_level.txt
style_doc-0.2.0.dist-info/RECORD
