Metadata-Version: 2.1
Name: style-doc
Version: 0.2.0
Summary: Black for Python docstrings and reStructuredText (rst)
Home-page: https://github.com/telekom/style-doc
Author: Philip May
Author-email: philip.may@t-systems.com
Maintainer: Philip May
License: UNKNOWN
Project-URL: Bug Tracker, https://github.com/telekom/style-doc/issues
Project-URL: Source Code, https://github.com/telekom/style-doc
Project-URL: Contributing, https://github.com/telekom/style-doc/blob/main/CONTRIBUTING.md
Project-URL: Code of Conduct, https://github.com/telekom/style-doc/blob/main/CODE_OF_CONDUCT.md
Keywords: automation formatter formatting docstring rst reStructuredText black linter linting
Platform: UNKNOWN
Classifier: Development Status :: 4 - Beta
Classifier: Intended Audience :: Developers
Classifier: License :: OSI Approved :: Apache Software License
Classifier: Programming Language :: Python :: 3
Classifier: Programming Language :: Python :: 3.6
Classifier: Programming Language :: Python :: 3.7
Classifier: Programming Language :: Python :: 3.8
Classifier: Programming Language :: Python :: 3.9
Classifier: Programming Language :: Python :: 3 :: Only
Classifier: Topic :: Software Development
Classifier: Topic :: Software Development :: Libraries
Classifier: Topic :: Software Development :: Libraries :: Python Modules
Classifier: Operating System :: OS Independent
Classifier: Topic :: Software Development :: Quality Assurance
Requires-Python: >=3.6
License-File: LICENSE
Provides-Extra: checking
Requires-Dist: black ; extra == 'checking'
Requires-Dist: flake8 ; extra == 'checking'
Requires-Dist: isort ; extra == 'checking'
Requires-Dist: mdformat ; extra == 'checking'
Requires-Dist: mypy ; extra == 'checking'
Requires-Dist: pylint ; extra == 'checking'
Requires-Dist: pylintfileheader ; extra == 'checking'
Provides-Extra: optional
Provides-Extra: testing
Requires-Dist: pytest ; extra == 'testing'
Requires-Dist: packaging ; extra == 'testing'
